{"name":"Overload WT R5","description":"1st rotation only, start BOL with 130%\nAll buff active, C6 Chev at 2 stk, 5 first hit NA Arle gain SoDP, Benny Alley\ngenerated JSON by NekoArc","targets":[{"weight":2,"path":["charged","dmg"],"hitMode":"global","reaction":null,"bonusStats":{"all_dmgInc":0.0,"atk":-1070.0,"atk_":-20.0,"pyro_dmg_":-55.0,"all_dmg_":0.0,"pyro_enemyRes_":0.0,"normal_dmgInc":0.0},"description":"non Bennett Chev Buff"},{"weight":2,"path":["skill","spikeDmg"],"hitMode":"global","reaction":null,"bonusStats":{"all_dmgInc":0.0,"atk":-1070.0,"atk_":-20.0,"pyro_dmg_":-55.0,"all_dmg_":0.0,"pyro_enemyRes_":0.0,"normal_dmgInc":0.0},"description":""},{"weight":2,"path":["skill","finalDmg"],"hitMode":"global","reaction":null,"bonusStats":{"all_dmgInc":0.0,"atk":-1070.0,"atk_":-20.0,"pyro_dmg_":-55.0,"all_dmg_":0.0,"pyro_enemyRes_":0.0,"normal_dmgInc":0.0},"description":""},{"weight":2,"path":["skill","sigilDmg"],"hitMode":"global","reaction":null,"bonusStats":{"all_dmgInc":0.0,"atk":-1070.0,"atk_":-20.0,"pyro_dmg_":-55.0,"all_dmg_":0.0,"pyro_enemyRes_":0.0,"normal_dmgInc":0.0},"description":""},{"weight":2,"path":["normal","0"],"hitMode":"global","reaction":null,"bonusStats":{"all_dmgInc":0.0,"atk":0.0,"atk_":0.0,"pyro_dmg_":0.0,"all_dmg_":0.0,"pyro_enemyRes_":0.0,"normal_dmgInc":1200.0},"description":""},{"weight":2,"path":["normal","0"],"hitMode":"global","reaction":null,"bonusStats":{"all_dmgInc":-5748.40777521223,"atk":0.0,"atk_":0.0,"pyro_dmg_":0.0,"all_dmg_":0.0,"pyro_enemyRes_":0.0,"normal_dmgInc":0.0},"description":""},{"weight":2,"path":["normal","0"],"hitMode":"global","reaction":null,"bonusStats":{"all_dmgInc":-9349.199190877014,"atk":0.0,"atk_":0.0,"pyro_dmg_":0.0,"all_dmg_":0.0,"pyro_enemyRes_":0.0,"normal_dmgInc":1200.0},"description":""},{"weight":2,"path":["normal","1"],"hitMode":"global","reaction":null,"bonusStats":{"all_dmgInc":-1153.9837575000001,"atk":0.0,"atk_":0.0,"pyro_dmg_":0.0,"all_dmg_":0.0,"pyro_enemyRes_":0.0,"normal_dmgInc":1200.0},"description":""},{"weight":2,"path":["normal","1"],"hitMode":"global","reaction":null,"bonusStats":{"all_dmgInc":-6471.260949571313,"atk":0.0,"atk_":0.0,"pyro_dmg_":0.0,"all_dmg_":0.0,"pyro_enemyRes_":0.0,"normal_dmgInc":0.0},"description":""},{"weight":2,"path":["normal","1"],"hitMode":"global","reaction":null,"bonusStats":{"all_dmgInc":-9801.993009061238,"atk":0.0,"atk_":0.0,"pyro_dmg_":0.0,"all_dmg_":0.0,"pyro_enemyRes_":0.0,"normal_dmgInc":1200.0},"description":""},{"weight":2,"path":["normal","2"],"hitMode":"global","reaction":null,"bonusStats":{"all_dmgInc":-2221.418733187498,"atk":0.0,"atk_":0.0,"pyro_dmg_":0.0,"all_dmg_":0.0,"pyro_enemyRes_":0.0,"normal_dmgInc":1200.0},"description":""},{"weight":2,"path":["normal","2"],"hitMode":"global","reaction":null,"bonusStats":{"all_dmgInc":-7139.900135853464,"atk":0.0,"atk_":0.0,"pyro_dmg_":0.0,"all_dmg_":0.0,"pyro_enemyRes_":0.0,"normal_dmgInc":0.0},"description":""},{"weight":2,"path":["normal","2"],"hitMode":"global","reaction":null,"bonusStats":{"all_dmgInc":-10220.827290881643,"atk":0.0,"atk_":0.0,"pyro_dmg_":0.0,"all_dmg_":0.0,"pyro_enemyRes_":0.0,"normal_dmgInc":1200.0},"description":""},{"weight":2,"path":["normal","3"],"hitMode":"global","reaction":null,"bonusStats":{"all_dmgInc":-3208.7960856984373,"atk":0.0,"atk_":0.0,"pyro_dmg_":0.0,"all_dmg_":0.0,"pyro_enemyRes_":0.0,"normal_dmgInc":1200.0},"description":""},{"weight":2,"path":["normal","3"],"hitMode":"global","reaction":null,"bonusStats":{"all_dmgInc":-4122.120136771053,"atk":0.0,"atk_":0.0,"pyro_dmg_":0.0,"all_dmg_":0.0,"pyro_enemyRes_":0.0,"normal_dmgInc":1200.0},"description":""},{"weight":2,"path":["normal","3"],"hitMode":"global","reaction":null,"bonusStats":{"all_dmgInc":-7758.391383164453,"atk":0.0,"atk_":0.0,"pyro_dmg_":0.0,"all_dmg_":0.0,"pyro_enemyRes_":0.0,"normal_dmgInc":0.0},"description":""},{"weight":2,"path":["normal","3"],"hitMode":"global","reaction":null,"bonusStats":{"all_dmgInc":-8330.495786927118,"atk":0.0,"atk_":0.0,"pyro_dmg_":0.0,"all_dmg_":0.0,"pyro_enemyRes_":0.0,"normal_dmgInc":0.0},"description":""},{"weight":2,"path":["normal","3"],"hitMode":"global","reaction":null,"bonusStats":{"all_dmgInc":-10608.24900156552,"atk":0.0,"atk_":0.0,"pyro_dmg_":0.0,"all_dmg_":0.0,"pyro_enemyRes_":0.0,"normal_dmgInc":1200.0},"description":""},{"weight":2,"path":["normal","3"],"hitMode":"global","reaction":null,"bonusStats":{"all_dmgInc":-10966.614083948107,"atk":0.0,"atk_":0.0,"pyro_dmg_":0.0,"all_dmg_":0.0,"pyro_enemyRes_":0.0,"normal_dmgInc":1200.0},"description":""},{"weight":2,"path":["normal","4"],"hitMode":"global","reaction":null,"bonusStats":{"all_dmgInc":-4966.944884013223,"atk":0.0,"atk_":0.0,"pyro_dmg_":0.0,"all_dmg_":0.0,"pyro_enemyRes_":0.0,"normal_dmgInc":0.0},"description":""},{"weight":2,"path":["normal","4"],"hitMode":"global","reaction":null,"bonusStats":{"all_dmgInc":-8859.692360407586,"atk":0.0,"atk_":0.0,"pyro_dmg_":0.0,"all_dmg_":0.0,"pyro_enemyRes_":0.0,"normal_dmgInc":0.0},"description":""},{"weight":2,"path":["normal","4"],"hitMode":"global","reaction":null,"bonusStats":{"all_dmgInc":-11298.101785152,"atk":0.0,"atk_":0.0,"pyro_dmg_":0.0,"all_dmg_":0.0,"pyro_enemyRes_":0.0,"normal_dmgInc":0.0},"description":""},{"weight":15,"path":["reaction","overloaded"],"hitMode":"hit","reaction":null,"bonusStats":{"all_dmgInc":0.0,"atk":0.0,"atk_":0.0,"pyro_dmg_":0.0,"all_dmg_":0.0,"pyro_enemyRes_":0.0,"normal_dmgInc":0.0},"description":""}]}